[{"ID":"8","SuraID":"2","VerseID":1,"surah":"Al-Baqarah"},{"ID":9,"SuraID":"2","VerseID":2,"surah":"Al-Baqarah"},{"ID":10,"SuraID":"2","VerseID":3,"surah":"Al-Baqarah"},{"ID":11,"SuraID":"2","VerseID":4,"surah":"Al-Baqarah"},{"ID":12,"SuraID":"2","VerseID":5,"surah":"Al-Baqarah"},{"ID":13,"SuraID":"2","VerseID":6,"surah":"Al-Baqarah"},{"ID":14,"SuraID":"2","VerseID":7,"surah":"Al-Baqarah"},{"ID":15,"SuraID":"2","VerseID":8,"surah":"Al-Baqarah"},{"ID":16,"SuraID":"2","VerseID":9,"surah":"Al-Baqarah"},{"ID":17,"SuraID":"2","VerseID":10,"surah":"Al-Baqarah"},{"ID":18,"SuraID":"2","VerseID":11,"surah":"Al-Baqarah"},{"ID":19,"SuraID":"2","VerseID":12,"surah":"Al-Baqarah"},{"ID":20,"SuraID":"2","VerseID":13,"surah":"Al-Baqarah"},{"ID":21,"SuraID":"2","VerseID":14,"surah":"Al-Baqarah"},{"ID":22,"SuraID":"2","VerseID":15,"surah":"Al-Baqarah"},{"ID":23,"SuraID":"2","VerseID":16,"surah":"Al-Baqarah"},{"ID":24,"SuraID":"2","VerseID":17,"surah":"Al-Baqarah"},{"ID":25,"SuraID":"2","VerseID":18,"surah":"Al-Baqarah"},{"ID":26,"SuraID":"2","VerseID":19,"surah":"Al-Baqarah"},{"ID":27,"SuraID":"2","VerseID":20,"surah":"Al-Baqarah"},{"ID":28,"SuraID":"2","VerseID":21,"surah":"Al-Baqarah"},{"ID":29,"SuraID":"2","VerseID":22,"surah":"Al-Baqarah"},{"ID":30,"SuraID":"2","VerseID":23,"surah":"Al-Baqarah"},{"ID":31,"SuraID":"2","VerseID":24,"surah":"Al-Baqarah"},{"ID":32,"SuraID":"2","VerseID":25,"surah":"Al-Baqarah"},{"ID":33,"SuraID":"2","VerseID":26,"surah":"Al-Baqarah"},{"ID":34,"SuraID":"2","VerseID":27,"surah":"Al-Baqarah"},{"ID":35,"SuraID":"2","VerseID":28,"surah":"Al-Baqarah"},{"ID":36,"SuraID":"2","VerseID":29,"surah":"Al-Baqarah"},{"ID":37,"SuraID":"2","VerseID":30,"surah":"Al-Baqarah"},{"ID":38,"SuraID":"2","VerseID":31,"surah":"Al-Baqarah"},{"ID":39,"SuraID":"2","VerseID":32,"surah":"Al-Baqarah"},{"ID":40,"SuraID":"2","VerseID":33,"surah":"Al-Baqarah"},{"ID":41,"SuraID":"2","VerseID":34,"surah":"Al-Baqarah"},{"ID":42,"SuraID":"2","VerseID":35,"surah":"Al-Baqarah"},{"ID":43,"SuraID":"2","VerseID":36,"surah":"Al-Baqarah"},{"ID":44,"SuraID":"2","VerseID":37,"surah":"Al-Baqarah"},{"ID":45,"SuraID":"2","VerseID":38,"surah":"Al-Baqarah"},{"ID":46,"SuraID":"2","VerseID":39,"surah":"Al-Baqarah"},{"ID":47,"SuraID":"2","VerseID":40,"surah":"Al-Baqarah"},{"ID":48,"SuraID":"2","VerseID":41,"surah":"Al-Baqarah"},{"ID":49,"SuraID":"2","VerseID":42,"surah":"Al-Baqarah"},{"ID":50,"SuraID":"2","VerseID":43,"surah":"Al-Baqarah"},{"ID":51,"SuraID":"2","VerseID":44,"surah":"Al-Baqarah"},{"ID":52,"SuraID":"2","VerseID":45,"surah":"Al-Baqarah"},{"ID":53,"SuraID":"2","VerseID":46,"surah":"Al-Baqarah"},{"ID":54,"SuraID":"2","VerseID":47,"surah":"Al-Baqarah"},{"ID":55,"SuraID":"2","VerseID":48,"surah":"Al-Baqarah"},{"ID":56,"SuraID":"2","VerseID":49,"surah":"Al-Baqarah"},{"ID":57,"SuraID":"2","VerseID":50,"surah":"Al-Baqarah"},{"ID":58,"SuraID":"2","VerseID":51,"surah":"Al-Baqarah"},{"ID":59,"SuraID":"2","VerseID":52,"surah":"Al-Baqarah"},{"ID":60,"SuraID":"2","VerseID":53,"surah":"Al-Baqarah"},{"ID":61,"SuraID":"2","VerseID":54,"surah":"Al-Baqarah"},{"ID":62,"SuraID":"2","VerseID":55,"surah":"Al-Baqarah"},{"ID":63,"SuraID":"2","VerseID":56,"surah":"Al-Baqarah"},{"ID":64,"SuraID":"2","VerseID":57,"surah":"Al-Baqarah"},{"ID":65,"SuraID":"2","VerseID":58,"surah":"Al-Baqarah"},{"ID":66,"SuraID":"2","VerseID":59,"surah":"Al-Baqarah"},{"ID":67,"SuraID":"2","VerseID":60,"surah":"Al-Baqarah"},{"ID":68,"SuraID":"2","VerseID":61,"surah":"Al-Baqarah"},{"ID":69,"SuraID":"2","VerseID":62,"surah":"Al-Baqarah"},{"ID":70,"SuraID":"2","VerseID":63,"surah":"Al-Baqarah"},{"ID":71,"SuraID":"2","VerseID":64,"surah":"Al-Baqarah"},{"ID":72,"SuraID":"2","VerseID":65,"surah":"Al-Baqarah"},{"ID":73,"SuraID":"2","VerseID":66,"surah":"Al-Baqarah"},{"ID":74,"SuraID":"2","VerseID":67,"surah":"Al-Baqarah"},{"ID":75,"SuraID":"2","VerseID":68,"surah":"Al-Baqarah"},{"ID":76,"SuraID":"2","VerseID":69,"surah":"Al-Baqarah"},{"ID":77,"SuraID":"2","VerseID":70,"surah":"Al-Baqarah"},{"ID":78,"SuraID":"2","VerseID":71,"surah":"Al-Baqarah"},{"ID":79,"SuraID":"2","VerseID":72,"surah":"Al-Baqarah"},{"ID":80,"SuraID":"2","VerseID":73,"surah":"Al-Baqarah"},{"ID":81,"SuraID":"2","VerseID":74,"surah":"Al-Baqarah"},{"ID":82,"SuraID":"2","VerseID":75,"surah":"Al-Baqarah"},{"ID":83,"SuraID":"2","VerseID":76,"surah":"Al-Baqarah"},{"ID":84,"SuraID":"2","VerseID":77,"surah":"Al-Baqarah"},{"ID":85,"SuraID":"2","VerseID":78,"surah":"Al-Baqarah"},{"ID":86,"SuraID":"2","VerseID":79,"surah":"Al-Baqarah"},{"ID":87,"SuraID":"2","VerseID":80,"surah":"Al-Baqarah"},{"ID":88,"SuraID":"2","VerseID":81,"surah":"Al-Baqarah"},{"ID":89,"SuraID":"2","VerseID":82,"surah":"Al-Baqarah"},{"ID":90,"SuraID":"2","VerseID":83,"surah":"Al-Baqarah"},{"ID":91,"SuraID":"2","VerseID":84,"surah":"Al-Baqarah"},{"ID":92,"SuraID":"2","VerseID":85,"surah":"Al-Baqarah"},{"ID":93,"SuraID":"2","VerseID":86,"surah":"Al-Baqarah"},{"ID":94,"SuraID":"2","VerseID":87,"surah":"Al-Baqarah"},{"ID":95,"SuraID":"2","VerseID":88,"surah":"Al-Baqarah"},{"ID":96,"SuraID":"2","VerseID":89,"surah":"Al-Baqarah"},{"ID":97,"SuraID":"2","VerseID":90,"surah":"Al-Baqarah"},{"ID":98,"SuraID":"2","VerseID":91,"surah":"Al-Baqarah"},{"ID":99,"SuraID":"2","VerseID":92,"surah":"Al-Baqarah"},{"ID":100,"SuraID":"2","VerseID":93,"surah":"Al-Baqarah"},{"ID":101,"SuraID":"2","VerseID":94,"surah":"Al-Baqarah"},{"ID":102,"SuraID":"2","VerseID":95,"surah":"Al-Baqarah"},{"ID":103,"SuraID":"2","VerseID":96,"surah":"Al-Baqarah"},{"ID":104,"SuraID":"2","VerseID":97,"surah":"Al-Baqarah"},{"ID":105,"SuraID":"2","VerseID":98,"surah":"Al-Baqarah"},{"ID":106,"SuraID":"2","VerseID":99,"surah":"Al-Baqarah"},{"ID":107,"SuraID":"2","VerseID":100,"surah":"Al-Baqarah"},{"ID":108,"SuraID":"2","VerseID":101,"surah":"Al-Baqarah"},{"ID":109,"SuraID":"2","VerseID":102,"surah":"Al-Baqarah"},{"ID":110,"SuraID":"2","VerseID":103,"surah":"Al-Baqarah"},{"ID":111,"SuraID":"2","VerseID":104,"surah":"Al-Baqarah"},{"ID":112,"SuraID":"2","VerseID":105,"surah":"Al-Baqarah"},{"ID":113,"SuraID":"2","VerseID":106,"surah":"Al-Baqarah"},{"ID":114,"SuraID":"2","VerseID":107,"surah":"Al-Baqarah"},{"ID":115,"SuraID":"2","VerseID":108,"surah":"Al-Baqarah"},{"ID":116,"SuraID":"2","VerseID":109,"surah":"Al-Baqarah"},{"ID":117,"SuraID":"2","VerseID":110,"surah":"Al-Baqarah"},{"ID":118,"SuraID":"2","VerseID":111,"surah":"Al-Baqarah"},{"ID":119,"SuraID":"2","VerseID":112,"surah":"Al-Baqarah"},{"ID":120,"SuraID":"2","VerseID":113,"surah":"Al-Baqarah"},{"ID":121,"SuraID":"2","VerseID":114,"surah":"Al-Baqarah"},{"ID":122,"SuraID":"2","VerseID":115,"surah":"Al-Baqarah"},{"ID":123,"SuraID":"2","VerseID":116,"surah":"Al-Baqarah"},{"ID":124,"SuraID":"2","VerseID":117,"surah":"Al-Baqarah"},{"ID":125,"SuraID":"2","VerseID":118,"surah":"Al-Baqarah"},{"ID":126,"SuraID":"2","VerseID":119,"surah":"Al-Baqarah"},{"ID":127,"SuraID":"2","VerseID":120,"surah":"Al-Baqarah"},{"ID":128,"SuraID":"2","VerseID":121,"surah":"Al-Baqarah"},{"ID":129,"SuraID":"2","VerseID":122,"surah":"Al-Baqarah"},{"ID":130,"SuraID":"2","VerseID":123,"surah":"Al-Baqarah"},{"ID":131,"SuraID":"2","VerseID":124,"surah":"Al-Baqarah"},{"ID":132,"SuraID":"2","VerseID":125,"surah":"Al-Baqarah"},{"ID":133,"SuraID":"2","VerseID":126,"surah":"Al-Baqarah"},{"ID":134,"SuraID":"2","VerseID":127,"surah":"Al-Baqarah"},{"ID":135,"SuraID":"2","VerseID":128,"surah":"Al-Baqarah"},{"ID":136,"SuraID":"2","VerseID":129,"surah":"Al-Baqarah"},{"ID":137,"SuraID":"2","VerseID":130,"surah":"Al-Baqarah"},{"ID":138,"SuraID":"2","VerseID":131,"surah":"Al-Baqarah"},{"ID":139,"SuraID":"2","VerseID":132,"surah":"Al-Baqarah"},{"ID":140,"SuraID":"2","VerseID":133,"surah":"Al-Baqarah"},{"ID":141,"SuraID":"2","VerseID":134,"surah":"Al-Baqarah"},{"ID":142,"SuraID":"2","VerseID":135,"surah":"Al-Baqarah"},{"ID":143,"SuraID":"2","VerseID":136,"surah":"Al-Baqarah"},{"ID":144,"SuraID":"2","VerseID":137,"surah":"Al-Baqarah"},{"ID":145,"SuraID":"2","VerseID":138,"surah":"Al-Baqarah"},{"ID":146,"SuraID":"2","VerseID":139,"surah":"Al-Baqarah"},{"ID":147,"SuraID":"2","VerseID":140,"surah":"Al-Baqarah"},{"ID":148,"SuraID":"2","VerseID":141,"surah":"Al-Baqarah"},{"ID":149,"SuraID":"2","VerseID":142,"surah":"Al-Baqarah"},{"ID":150,"SuraID":"2","VerseID":143,"surah":"Al-Baqarah"},{"ID":151,"SuraID":"2","VerseID":144,"surah":"Al-Baqarah"},{"ID":152,"SuraID":"2","VerseID":145,"surah":"Al-Baqarah"},{"ID":153,"SuraID":"2","VerseID":146,"surah":"Al-Baqarah"},{"ID":154,"SuraID":"2","VerseID":147,"surah":"Al-Baqarah"},{"ID":155,"SuraID":"2","VerseID":148,"surah":"Al-Baqarah"},{"ID":156,"SuraID":"2","VerseID":149,"surah":"Al-Baqarah"},{"ID":157,"SuraID":"2","VerseID":150,"surah":"Al-Baqarah"},{"ID":158,"SuraID":"2","VerseID":151,"surah":"Al-Baqarah"},{"ID":159,"SuraID":"2","VerseID":152,"surah":"Al-Baqarah"},{"ID":160,"SuraID":"2","VerseID":153,"surah":"Al-Baqarah"},{"ID":161,"SuraID":"2","VerseID":154,"surah":"Al-Baqarah"},{"ID":162,"SuraID":"2","VerseID":155,"surah":"Al-Baqarah"},{"ID":163,"SuraID":"2","VerseID":156,"surah":"Al-Baqarah"},{"ID":164,"SuraID":"2","VerseID":157,"surah":"Al-Baqarah"},{"ID":165,"SuraID":"2","VerseID":158,"surah":"Al-Baqarah"},{"ID":166,"SuraID":"2","VerseID":159,"surah":"Al-Baqarah"},{"ID":167,"SuraID":"2","VerseID":160,"surah":"Al-Baqarah"},{"ID":168,"SuraID":"2","VerseID":161,"surah":"Al-Baqarah"},{"ID":169,"SuraID":"2","VerseID":162,"surah":"Al-Baqarah"},{"ID":170,"SuraID":"2","VerseID":163,"surah":"Al-Baqarah"},{"ID":171,"SuraID":"2","VerseID":164,"surah":"Al-Baqarah"},{"ID":172,"SuraID":"2","VerseID":165,"surah":"Al-Baqarah"},{"ID":173,"SuraID":"2","VerseID":166,"surah":"Al-Baqarah"},{"ID":174,"SuraID":"2","VerseID":167,"surah":"Al-Baqarah"},{"ID":175,"SuraID":"2","VerseID":168,"surah":"Al-Baqarah"},{"ID":176,"SuraID":"2","VerseID":169,"surah":"Al-Baqarah"},{"ID":177,"SuraID":"2","VerseID":170,"surah":"Al-Baqarah"},{"ID":178,"SuraID":"2","VerseID":171,"surah":"Al-Baqarah"},{"ID":179,"SuraID":"2","VerseID":172,"surah":"Al-Baqarah"},{"ID":180,"SuraID":"2","VerseID":173,"surah":"Al-Baqarah"},{"ID":181,"SuraID":"2","VerseID":174,"surah":"Al-Baqarah"},{"ID":182,"SuraID":"2","VerseID":175,"surah":"Al-Baqarah"},{"ID":183,"SuraID":"2","VerseID":176,"surah":"Al-Baqarah"},{"ID":184,"SuraID":"2","VerseID":177,"surah":"Al-Baqarah"},{"ID":185,"SuraID":"2","VerseID":178,"surah":"Al-Baqarah"},{"ID":186,"SuraID":"2","VerseID":179,"surah":"Al-Baqarah"},{"ID":187,"SuraID":"2","VerseID":180,"surah":"Al-Baqarah"},{"ID":188,"SuraID":"2","VerseID":181,"surah":"Al-Baqarah"},{"ID":189,"SuraID":"2","VerseID":182,"surah":"Al-Baqarah"},{"ID":190,"SuraID":"2","VerseID":183,"surah":"Al-Baqarah"},{"ID":191,"SuraID":"2","VerseID":184,"surah":"Al-Baqarah"},{"ID":192,"SuraID":"2","VerseID":185,"surah":"Al-Baqarah"},{"ID":193,"SuraID":"2","VerseID":186,"surah":"Al-Baqarah"},{"ID":194,"SuraID":"2","VerseID":187,"surah":"Al-Baqarah"},{"ID":195,"SuraID":"2","VerseID":188,"surah":"Al-Baqarah"},{"ID":196,"SuraID":"2","VerseID":189,"surah":"Al-Baqarah"},{"ID":197,"SuraID":"2","VerseID":190,"surah":"Al-Baqarah"},{"ID":198,"SuraID":"2","VerseID":191,"surah":"Al-Baqarah"},{"ID":199,"SuraID":"2","VerseID":192,"surah":"Al-Baqarah"},{"ID":200,"SuraID":"2","VerseID":193,"surah":"Al-Baqarah"},{"ID":201,"SuraID":"2","VerseID":194,"surah":"Al-Baqarah"},{"ID":202,"SuraID":"2","VerseID":195,"surah":"Al-Baqarah"},{"ID":203,"SuraID":"2","VerseID":196,"surah":"Al-Baqarah"},{"ID":204,"SuraID":"2","VerseID":197,"surah":"Al-Baqarah"},{"ID":205,"SuraID":"2","VerseID":198,"surah":"Al-Baqarah"},{"ID":206,"SuraID":"2","VerseID":199,"surah":"Al-Baqarah"},{"ID":207,"SuraID":"2","VerseID":200,"surah":"Al-Baqarah"},{"ID":208,"SuraID":"2","VerseID":201,"surah":"Al-Baqarah"},{"ID":209,"SuraID":"2","VerseID":202,"surah":"Al-Baqarah"},{"ID":210,"SuraID":"2","VerseID":203,"surah":"Al-Baqarah"},{"ID":211,"SuraID":"2","VerseID":204,"surah":"Al-Baqarah"},{"ID":212,"SuraID":"2","VerseID":205,"surah":"Al-Baqarah"},{"ID":213,"SuraID":"2","VerseID":206,"surah":"Al-Baqarah"},{"ID":214,"SuraID":"2","VerseID":207,"surah":"Al-Baqarah"},{"ID":215,"SuraID":"2","VerseID":208,"surah":"Al-Baqarah"},{"ID":216,"SuraID":"2","VerseID":209,"surah":"Al-Baqarah"},{"ID":217,"SuraID":"2","VerseID":210,"surah":"Al-Baqarah"},{"ID":218,"SuraID":"2","VerseID":211,"surah":"Al-Baqarah"},{"ID":219,"SuraID":"2","VerseID":212,"surah":"Al-Baqarah"},{"ID":220,"SuraID":"2","VerseID":213,"surah":"Al-Baqarah"},{"ID":221,"SuraID":"2","VerseID":214,"surah":"Al-Baqarah"},{"ID":222,"SuraID":"2","VerseID":215,"surah":"Al-Baqarah"},{"ID":223,"SuraID":"2","VerseID":216,"surah":"Al-Baqarah"},{"ID":224,"SuraID":"2","VerseID":217,"surah":"Al-Baqarah"},{"ID":225,"SuraID":"2","VerseID":218,"surah":"Al-Baqarah"},{"ID":226,"SuraID":"2","VerseID":219,"surah":"Al-Baqarah"},{"ID":227,"SuraID":"2","VerseID":220,"surah":"Al-Baqarah"},{"ID":228,"SuraID":"2","VerseID":221,"surah":"Al-Baqarah"},{"ID":229,"SuraID":"2","VerseID":222,"surah":"Al-Baqarah"},{"ID":230,"SuraID":"2","VerseID":223,"surah":"Al-Baqarah"},{"ID":231,"SuraID":"2","VerseID":224,"surah":"Al-Baqarah"},{"ID":232,"SuraID":"2","VerseID":225,"surah":"Al-Baqarah"},{"ID":233,"SuraID":"2","VerseID":226,"surah":"Al-Baqarah"},{"ID":234,"SuraID":"2","VerseID":227,"surah":"Al-Baqarah"},{"ID":235,"SuraID":"2","VerseID":228,"surah":"Al-Baqarah"},{"ID":236,"SuraID":"2","VerseID":229,"surah":"Al-Baqarah"},{"ID":237,"SuraID":"2","VerseID":230,"surah":"Al-Baqarah"},{"ID":238,"SuraID":"2","VerseID":231,"surah":"Al-Baqarah"},{"ID":239,"SuraID":"2","VerseID":232,"surah":"Al-Baqarah"},{"ID":240,"SuraID":"2","VerseID":233,"surah":"Al-Baqarah"},{"ID":241,"SuraID":"2","VerseID":234,"surah":"Al-Baqarah"},{"ID":242,"SuraID":"2","VerseID":235,"surah":"Al-Baqarah"},{"ID":243,"SuraID":"2","VerseID":236,"surah":"Al-Baqarah"},{"ID":244,"SuraID":"2","VerseID":237,"surah":"Al-Baqarah"},{"ID":245,"SuraID":"2","VerseID":238,"surah":"Al-Baqarah"},{"ID":246,"SuraID":"2","VerseID":239,"surah":"Al-Baqarah"},{"ID":247,"SuraID":"2","VerseID":240,"surah":"Al-Baqarah"},{"ID":248,"SuraID":"2","VerseID":241,"surah":"Al-Baqarah"},{"ID":249,"SuraID":"2","VerseID":242,"surah":"Al-Baqarah"},{"ID":250,"SuraID":"2","VerseID":243,"surah":"Al-Baqarah"},{"ID":251,"SuraID":"2","VerseID":244,"surah":"Al-Baqarah"},{"ID":252,"SuraID":"2","VerseID":245,"surah":"Al-Baqarah"},{"ID":253,"SuraID":"2","VerseID":246,"surah":"Al-Baqarah"},{"ID":254,"SuraID":"2","VerseID":247,"surah":"Al-Baqarah"},{"ID":255,"SuraID":"2","VerseID":248,"surah":"Al-Baqarah"},{"ID":256,"SuraID":"2","VerseID":249,"surah":"Al-Baqarah"},{"ID":257,"SuraID":"2","VerseID":250,"surah":"Al-Baqarah"},{"ID":258,"SuraID":"2","VerseID":251,"surah":"Al-Baqarah"},{"ID":259,"SuraID":"2","VerseID":252,"surah":"Al-Baqarah"},{"ID":260,"SuraID":"2","VerseID":253,"surah":"Al-Baqarah"},{"ID":261,"SuraID":"2","VerseID":254,"surah":"Al-Baqarah"},{"ID":262,"SuraID":"2","VerseID":255,"surah":"Al-Baqarah"},{"ID":263,"SuraID":"2","VerseID":256,"surah":"Al-Baqarah"},{"ID":264,"SuraID":"2","VerseID":257,"surah":"Al-Baqarah"},{"ID":265,"SuraID":"2","VerseID":258,"surah":"Al-Baqarah"},{"ID":266,"SuraID":"2","VerseID":259,"surah":"Al-Baqarah"},{"ID":267,"SuraID":"2","VerseID":260,"surah":"Al-Baqarah"},{"ID":268,"SuraID":"2","VerseID":261,"surah":"Al-Baqarah"},{"ID":269,"SuraID":"2","VerseID":262,"surah":"Al-Baqarah"},{"ID":270,"SuraID":"2","VerseID":263,"surah":"Al-Baqarah"},{"ID":271,"SuraID":"2","VerseID":264,"surah":"Al-Baqarah"},{"ID":272,"SuraID":"2","VerseID":265,"surah":"Al-Baqarah"},{"ID":273,"SuraID":"2","VerseID":266,"surah":"Al-Baqarah"},{"ID":274,"SuraID":"2","VerseID":267,"surah":"Al-Baqarah"},{"ID":275,"SuraID":"2","VerseID":268,"surah":"Al-Baqarah"},{"ID":276,"SuraID":"2","VerseID":269,"surah":"Al-Baqarah"},{"ID":277,"SuraID":"2","VerseID":270,"surah":"Al-Baqarah"},{"ID":278,"SuraID":"2","VerseID":271,"surah":"Al-Baqarah"},{"ID":279,"SuraID":"2","VerseID":272,"surah":"Al-Baqarah"},{"ID":280,"SuraID":"2","VerseID":273,"surah":"Al-Baqarah"},{"ID":281,"SuraID":"2","VerseID":274,"surah":"Al-Baqarah"},{"ID":282,"SuraID":"2","VerseID":275,"surah":"Al-Baqarah"},{"ID":283,"SuraID":"2","VerseID":276,"surah":"Al-Baqarah"},{"ID":284,"SuraID":"2","VerseID":277,"surah":"Al-Baqarah"},{"ID":285,"SuraID":"2","VerseID":278,"surah":"Al-Baqarah"},{"ID":286,"SuraID":"2","VerseID":279,"surah":"Al-Baqarah"},{"ID":287,"SuraID":"2","VerseID":280,"surah":"Al-Baqarah"},{"ID":288,"SuraID":"2","VerseID":281,"surah":"Al-Baqarah"},{"ID":289,"SuraID":"2","VerseID":282,"surah":"Al-Baqarah"},{"ID":290,"SuraID":"2","VerseID":283,"surah":"Al-Baqarah"},{"ID":291,"SuraID":"2","VerseID":284,"surah":"Al-Baqarah"},{"ID":292,"SuraID":"2","VerseID":285,"surah":"Al-Baqarah"},{"ID":293,"SuraID":"2","VerseID":286,"surah":"Al-Baqarah"}]